secval-0.1.3.dist-info/METADATA
secval-0.1.3.dist-info/WHEEL
secval-0.1.3.dist-info/licenses/LICENSE
secval/__init__.py
secval/_secval.cpython-313-darwin.so
secval/py.typed
secval-0.1.3.dist-info/RECORD
