Metadata-Version: 2.4
Name: secval
Version: 0.1.3
Classifier: Development Status :: 4 - Beta
Classifier: Intended Audience :: Developers
Classifier: License :: OSI Approved :: MIT License
Classifier: Programming Language :: Python :: 3
Classifier: Programming Language :: Python :: 3.11
Classifier: Programming Language :: Python :: 3.12
Classifier: Programming Language :: Python :: 3.13
Classifier: Programming Language :: Rust
Classifier: Topic :: Software Development :: Libraries :: Python Modules
Classifier: Topic :: Security
Classifier: Typing :: Typed
Requires-Dist: pytest>=7.0 ; extra == 'dev'
Requires-Dist: pytest-benchmark>=4.0 ; extra == 'dev'
Requires-Dist: maturin>=1.4 ; extra == 'dev'
Provides-Extra: dev
License-File: LICENSE
Summary: A high-performance, security-focused Python validation library written in Rust
Keywords: validation,security,sanitization,pydantic-alternative,rust
Author-email: Samuel Avike <samuelavike@gmail.com>
License: MIT
Requires-Python: >=3.11, <3.14
Project-URL: Homepage, https://github.com/samuelavike1/secval
Project-URL: Repository, https://github.com/samuelavike1/secval
Project-URL: Documentation, https://github.com/samuelavike1/secval#readme
